src/alu.vhd
library IEEE;
use IEEE.std_logic_1164.all;
use IEEE.numeric_std.all;

entity ALU is
    generic (
        ARITHMETIC_OPERATION_ADD: std_logic_vector(7 downto 0) := x"00";
        ARITHMETIC_OPERATION_AND: std_logic_vector(7 downto 0) := x"01";
        ARITHMETIC_OPERATION_OR: std_logic_vector(7 downto 0)  := x"02";
        ARITHMETIC_OPERATION_SUB: std_logic_vector(7 downto 0) := x"03";
        ARITHMETIC_OPERATION_SHL: std_logic_vector(7 downto 0) := x"04";
        ARITHMETIC_OPERATION_NOT: std_logic_vector(7 downto 0) := x"05";
        ARITHMETIC_OPERATION_SHA: std_logic_vector(7 downto 0) := x"06";
        ARITHMETIC_OPERATION_XOR: std_logic_vector(7 downto 0) := x"07"
        --ARITHMETIC_OPERATION_ADD: unsigned(7 downto 0) := x"00";
        --ARITHMETIC_OPERATION_AND: unsigned(7 downto 0) := x"01"
        );
    

    port (
        
        operation : in std_logic_vector (7 downto 0);
        cmp_alu : in std_logic;
        A : in std_logic_vector (7 downto 0);
        B : in std_logic_vector (7 downto 0);
        clk: in STD_LOGIC;
        dataOut : out std_logic_vector (7 downto 0);
        z:     out STD_LOGIC;    
        ovf:   out STD_LOGIC
    );
    
end entity;

architecture arch of ALU is

begin

    --if rising_edge(clk) then
        process(A,B, operation, cmp_alu)
            variable temp : unsigned(8 downto 0);
            variable op :   unsigned(7 downto 0);
            variable temp_A : unsigned(7 downto 0); 
            variable temp_B : unsigned(7 downto 0);
        begin
            op := resize(unsigned(operation),8);
            temp_A := resize(unsigned(A),8);
            temp_B := resize(unsigned(B),8);
            -- COMPARATOR
            
            if cmp_alu = '1' then
                dataOut <= x"FF";
            else


            -- TODO case is not working
            --case op is
            --    when ARITHMETIC_OPERATION_ADD =>
            --    temp := resize(unsigned(A), temp'length) + unsigned(B);
            --    dataOut <= std_logic_vector(resize(temp,8));
            --    z <= '1' when temp = 0 else '0';
            --    ovf <= '1' when temp > 255 else '0';
            --    when others => dataOut <= x"AB";
            --    z <= '1';
            --    ovf <= '1';
            --end case;

            if operation = ARITHMETIC_OPERATION_ADD then
                temp := resize(unsigned(A), temp'length) + unsigned(B);
                dataOut <= std_logic_vector(resize(temp,8));
                z <= '1' when temp = 0 else '0';
                ovf <= '1' when temp > 255 else '0';
            elsif operation = ARITHMETIC_OPERATION_SUB then
                temp := resize(unsigned(A), temp'length) - unsigned(B);
                z <= '1' when temp = 0 else '0';
                dataOut <= std_logic_vector(resize(temp,8));
            elsif operation = ARITHMETIC_OPERATION_AND then
                temp := resize(unsigned(A and B),temp'length);
                dataOut <= std_logic_vector(resize(temp,8));
                z <= '1' when temp = 0 else '0';
                ovf <= '0';
            elsif operation = ARITHMETIC_OPERATION_OR then
                temp := resize(unsigned(A or B),temp'length);
                dataOut <= std_logic_vector(resize(temp,8));
                z <= '1' when temp = 0 else '0';
                ovf <= '0';
            elsif operation = ARITHMETIC_OPERATION_XOR then
                temp := resize(unsigned(A xor B),temp'length);
                dataOut <= std_logic_vector(resize(temp,8));
                z <= '1' when temp = 0 else '0';
                ovf <= '0';
            elsif operation = ARITHMETIC_OPERATION_NOT then
                temp := resize(unsigned(NOT A),temp'length);
                dataOut <= std_logic_vector(resize(temp,8));
                z <= '1' when temp = 0 else '0';
                ovf <= '0'; 
            elsif operation = ARITHMETIC_OPERATION_SHL then
                temp := resize(unsigned(to_stdlogicvector(to_bitvector(A) sll to_integer(unsigned(B)))),temp'length);
                dataOut <= std_logic_vector(resize(temp,8));
                --to_stdlogicvector(to_bitvector(A) sra to_integer(unsigned(B)));
                z <= '1' when temp = 0 else '0';
                ovf <= '0'; 
            elsif operation = ARITHMETIC_OPERATION_SHA then
                temp := resize(unsigned(to_stdlogicvector(to_bitvector(A) sla to_integer(signed(B)))),temp'length);
                dataOut <= std_logic_vector(resize(temp,8));
                --to_stdlogicvector(to_bitvector(A) sra to_integer(unsigned(B)));
                z <= '1' when temp = 0 else '0';
                ovf <= '0'; 
            else
                dataOut <= x"AB";
                z <= '1';
                ovf <= '1';
            end if;
        end if;
        end process;
end architecture;

src/alu_tb.vhd
library IEEE;
use IEEE.std_logic_1164.all;
use IEEE.numeric_std.all;
 

 
ENTITY ALU_tb IS
END ALU_tb;
 
ARCHITECTURE behavior OF ALU_tb IS 
 
    -- Component Declaration for the Unit Under Test (UUT)
 
  

    COMPONENT ALU is
        port (
            
            operation : in std_logic_vector (7 downto 0);
            cmp_alu : in std_logic;
            A : in std_logic_vector (7 downto 0);
            B : in std_logic_vector (7 downto 0);
            clk: in STD_LOGIC;
            dataOut : out std_logic_vector (7 downto 0);
            z:     out STD_LOGIC;    
            ovf:   out STD_LOGIC
        );
    END COMPONENT;
    

   --Inputs
   signal A : std_logic_vector(7 downto 0);
   signal B : std_logic_vector(7 downto 0);

 	--Outputs
   signal dataOut : std_logic_vector(7 downto 0);


   signal operation : std_logic_vector (7 downto 0);
   signal   clk:  STD_LOGIC;
   
   signal z:     STD_LOGIC;    
   signal ovf:    STD_LOGIC;

   signal cmp_alu :  std_logic;

   -- No clocks detected in port list. Replace <clock> below with 
   -- appropriate port name 
 
   -- constant <clock>_period : time := 10 ns;
 
BEGIN
 
	-- Instantiate the Unit Under Test (UUT)
   uut: ALU PORT MAP (
          A => A,
          B => B,
          dataOut => dataOut,
          z => z,
          ovf => ovf,
          clk => clk,
          operation => operation,
          cmp_alu => cmp_alu
        );

   -- Clock process definitions
   -- <clock>_process :process
   -- begin
	-- 	<clock> <= '0';
	-- 	wait for <clock>_period/2;
	-- 	<clock> <= '1';
	-- 	wait for <clock>_period/2;
   -- end process;
 

   -- Stimulus process
   stim_proc: process
   begin		
      -- hold reset state for 100 ns.
     -- wait for 1 ns;	

      -- wait for <clock>_period*10;

      -- insert stimulus here 
      operation <= x"00";
      cmp_alu <= '0';
		for i in 10 downto 0 loop
           A <= std_logic_vector(to_unsigned(i,8)); 
           B <= std_logic_vector(to_unsigned(10-i,8)); 
			  wait for 1 us;
      end loop;
      wait for 1 us;
      A <= x"00";
      B <= x"00";
      wait for 1 us;
      A <= x"FF";
      B <= x"01";
      wait for 1 us;
      operation <= x"AB";
      wait for 1 us;

      -- TEST AND
      operation <= x"01";
      A <= x"FF";
      B <= x"00";
      wait for 1 us;
      A <= x"F0";
      B <= x"01";
      wait for 1 us;
      A <= x"AB";
      B <= x"FF";
      wait for 1 us;
      A <= x"FF";
      B <= x"FF";
      wait for 1 us;
      -- TEST OR
      operation <= x"02";
      A <= x"FF";
      B <= x"00";
      wait for 1 us;
      A <= x"00";
      B <= x"01";
      wait for 1 us;
     -- TEST SUB
     operation <= x"03";
     for i in 7 downto 0 
     loop
        A <= std_logic_vector(to_unsigned(i,8)); 
        B <= std_logic_vector(to_unsigned(7-i,8)); 
           wait for 1 us;
      end loop;

      -- TEST SHL
      operation <= x"04";
      A <= x"01";
      B <= x"01";
      wait for 1 us;

      -- TEST NOT
      operation <= x"05";
      A <= x"FF";
      B <= x"05";
      wait for 1 us;

      -- TEST SHA
      operation <= x"06";
      A <= x"01";
      B <= x"01";
      wait for 1 us;

      -- TEST XOR
      operation <= x"07";
      A <= x"FF";
      B <= x"FF";
      wait for 1 us;

      cmp_alu <= '1';
      wait for 1 us;
      wait;
   end process;

END;

src/alu_tb.vcd
$date
  Fri Jan 21 00:03:25 2022
$end
$version
  GHDL v0
$end
$timescale
  1 fs
$end
$scope module standard $end
$upscope $end
$scope module textio $end
$upscope $end
$scope module std_logic_1164 $end
$upscope $end
$scope module numeric_std $end
$upscope $end
$scope module alu_tb $end
$var reg 8 ! a[7:0] $end
$var reg 8 " b[7:0] $end
$var reg 8 # dataout[7:0] $end
$var reg 8 $ operation[7:0] $end
$var reg 1 % clk $end
$var reg 1 & z $end
$var reg 1 ' ovf $end
$var reg 1 ( cmp_alu $end
$scope module uut $end
$var reg 8 ) operation[7:0] $end
$var reg 1 * cmp_alu $end
$var reg 8 + a[7:0] $end
$var reg 8 , b[7:0] $end
$var reg 1 - clk $end
$var reg 8 . dataout[7:0] $end
$var reg 1 / z $end
$var reg 1 0 ovf $end
$upscope $end
$upscope $end
$enddefinitions $end
#0
b00001010 !
b00000000 "
b00001010 #
b00000000 $
U%
0&
0'
0(
b00000000 )
0*
b00001010 +
b00000000 ,
U-
b00001010 .
0/
00
#1000000000
b00001001 !
b00000001 "
b00001001 +
b00000001 ,
#2000000000
b00001000 !
b00000010 "
b00001000 +
b00000010 ,
#3000000000
b00000111 !
b00000011 "
b00000111 +
b00000011 ,
#4000000000
b00000110 !
b00000100 "
b00000110 +
b00000100 ,
#5000000000
b00000101 !
b00000101 "
b00000101 +
b00000101 ,
#6000000000
b00000100 !
b00000110 "
b00000100 +
b00000110 ,
#7000000000
b00000011 !
b00000111 "
b00000011 +
b00000111 ,
#8000000000
b00000010 !
b00001000 "
b00000010 +
b00001000 ,
#9000000000
b00000001 !
b00001001 "
b00000001 +
b00001001 ,
#10000000000
b00000000 !
b00001010 "
b00000000 +
b00001010 ,
#11000000000
#12000000000
b00000000 "
b00000000 #
1&
b00000000 ,
b00000000 .
1/
#13000000000
b11111111 !
b00000001 "
0&
1'
b11111111 +
b00000001 ,
0/
10
#14000000000
b10101011 #
b10101011 $
1&
b10101011 )
b10101011 .
1/
#15000000000
b00000000 "
b00000000 #
b00000001 $
0'
b00000001 )
b00000000 ,
b00000000 .
00
#16000000000
b11110000 !
b00000001 "
b11110000 +
b00000001 ,
#17000000000
b10101011 !
b11111111 "
b10101011 #
0&
b10101011 +
b11111111 ,
b10101011 .
0/
#18000000000
b11111111 !
b11111111 #
b11111111 +
b11111111 .
#19000000000
b00000000 "
b00000010 $
b00000010 )
b00000000 ,
#20000000000
b00000000 !
b00000001 "
b00000001 #
b00000000 +
b00000001 ,
b00000001 .
#21000000000
b00000111 !
b00000000 "
b00000111 #
b00000011 $
b00000011 )
b00000111 +
b00000000 ,
b00000111 .
#22000000000
b00000110 !
b00000001 "
b00000101 #
b00000110 +
b00000001 ,
b00000101 .
#23000000000
b00000101 !
b00000010 "
b00000011 #
b00000101 +
b00000010 ,
b00000011 .
#24000000000
b00000100 !
b00000011 "
b00000001 #
b00000100 +
b00000011 ,
b00000001 .
#25000000000
b00000011 !
b00000100 "
b11111111 #
b00000011 +
b00000100 ,
b11111111 .
#26000000000
b00000010 !
b00000101 "
b11111101 #
b00000010 +
b00000101 ,
b11111101 .
#27000000000
b00000001 !
b00000110 "
b11111011 #
b00000001 +
b00000110 ,
b11111011 .
#28000000000
b00000000 !
b00000111 "
b11111001 #
b00000000 +
b00000111 ,
b11111001 .
#29000000000
b00000001 !
b00000001 "
b00000010 #
b00000100 $
b00000100 )
b00000001 +
b00000001 ,
b00000010 .
#30000000000
b11111111 !
b00000101 "
b00000000 #
b00000101 $
1&
b00000101 )
b11111111 +
b00000101 ,
b00000000 .
1/
#31000000000
b00000001 !
b00000001 "
b00000011 #
b00000110 $
0&
b00000110 )
b00000001 +
b00000001 ,
b00000011 .
0/
#32000000000
b11111111 !
b11111111 "
b00000000 #
b00000111 $
1&
b00000111 )
b11111111 +
b11111111 ,
b00000000 .
1/
#33000000000
b11111111 #
1(
1*
b11111111 .
