src/alu.vhd
library IEEE;
use IEEE.std_logic_1164.all;
use IEEE.numeric_std.all;

entity ALU is
    generic (
        ARITHMETIC_OPERATION_ADD: std_logic_vector(7 downto 0) := x"00";
        ARITHMETIC_OPERATION_AND: std_logic_vector(7 downto 0) := x"01"
        --ARITHMETIC_OPERATION_ADD: unsigned(7 downto 0) := x"00";
        --ARITHMETIC_OPERATION_AND: unsigned(7 downto 0) := x"01"
        );
    

    port (
        
        operation : in std_logic_vector (7 downto 0);
        A : in std_logic_vector (7 downto 0);
        B : in std_logic_vector (7 downto 0);
        clk: in STD_LOGIC;
        dataOut : out std_logic_vector (7 downto 0);
        z:     out STD_LOGIC;    
        ovf:   out STD_LOGIC
    );
    
end entity;

architecture arch of ALU is

begin

    --if rising_edge(clk) then
        process(A,B, operation)
            variable temp : unsigned(8 downto 0);
            variable op :   unsigned(7 downto 0); 
        begin
            op := resize(unsigned(operation),8);
            --case op is
            --    when ARITHMETIC_OPERATION_ADD =>
            --    temp := resize(unsigned(A), temp'length) + unsigned(B);
            --    dataOut <= std_logic_vector(resize(temp,8));
            --    z <= '1' when temp = 0 else '0';
            --    ovf <= '1' when temp > 255 else '0';
            --    when others => dataOut <= x"AB";
            --    z <= '1';
            --    ovf <= '1';
            --end case;

            if operation = ARITHMETIC_OPERATION_ADD then
                temp := resize(unsigned(A), temp'length) + unsigned(B);
                dataOut <= std_logic_vector(resize(temp,8));
                z <= '1' when temp = 0 else '0';
                ovf <= '1' when temp > 255 else '0';
            elsif operation = ARITHMETIC_OPERATION_AND then
                dataOut <= A and B;
                z <= '0';
                ovf <= '0';
            else
                dataOut <= x"AB";
                z <= '1';
                ovf <= '1';
            end if;
        end process;
    --end if;
    -- dataOut <= memory(to_integer(unsigned(address))) when to_integer(unsigned(address)) < 5 else
	-- x"ABAB" when 	to_integer(unsigned(address)) > 4;

end architecture;

src/alu_tb.vhd
library IEEE;
use IEEE.std_logic_1164.all;
use IEEE.numeric_std.all;
 

 
ENTITY ALU_tb IS
END ALU_tb;
 
ARCHITECTURE behavior OF ALU_tb IS 
 
    -- Component Declaration for the Unit Under Test (UUT)
 
  

    COMPONENT ALU is
        port (
            
            operation : in std_logic_vector (7 downto 0);
            A : in std_logic_vector (7 downto 0);
            B : in std_logic_vector (7 downto 0);
            clk: in STD_LOGIC;
            dataOut : out std_logic_vector (7 downto 0);
            z:     out STD_LOGIC;    
            ovf:   out STD_LOGIC
        );
    END COMPONENT;
    

   --Inputs
   signal A : std_logic_vector(7 downto 0);
   signal B : std_logic_vector(7 downto 0);

 	--Outputs
   signal dataOut : std_logic_vector(7 downto 0);


   signal operation : std_logic_vector (7 downto 0);
   signal   clk:  STD_LOGIC;
   
   signal z:     STD_LOGIC;    
   signal ovf:    STD_LOGIC;

   -- No clocks detected in port list. Replace <clock> below with 
   -- appropriate port name 
 
   -- constant <clock>_period : time := 10 ns;
 
BEGIN
 
	-- Instantiate the Unit Under Test (UUT)
   uut: ALU PORT MAP (
          A => A,
          B => B,
          dataOut => dataOut,
          z => z,
          ovf => ovf,
          clk => clk,
          operation => operation
        );

   -- Clock process definitions
   -- <clock>_process :process
   -- begin
	-- 	<clock> <= '0';
	-- 	wait for <clock>_period/2;
	-- 	<clock> <= '1';
	-- 	wait for <clock>_period/2;
   -- end process;
 

   -- Stimulus process
   stim_proc: process
   begin		
      -- hold reset state for 100 ns.
     -- wait for 1 ns;	

      -- wait for <clock>_period*10;

      -- insert stimulus here 
      operation <= x"00";
		for i in 7 downto 0 loop
           A <= std_logic_vector(to_unsigned(i,8)); 
           B <= std_logic_vector(to_unsigned(7-i,8)); 
			  wait for 1 us;
      end loop;
      wait for 1 us;
      A <= x"00";
      B <= x"00";
      wait for 1 us;
      A <= x"FF";
      B <= x"01";
      wait for 1 us;
      operation <= x"AB";
      wait for 1 us;

      -- TEST AND
      operation <= x"01";
      A <= x"FF";
      B <= x"00";
      wait for 1 us;
      A <= x"F0";
      B <= x"01";
      wait for 1 us;
      A <= x"AB";
      B <= x"FF";
      wait for 1 us;
      A <= x"FF";
      B <= x"FF";
      wait for 1 us;


      wait;
   end process;

END;

src/alu_tb.vcd
$date
  Thu Jan 20 17:05:45 2022
$end
$version
  GHDL v0
$end
$timescale
  1 fs
$end
$scope module standard $end
$upscope $end
$scope module textio $end
$upscope $end
$scope module std_logic_1164 $end
$upscope $end
$scope module numeric_std $end
$upscope $end
$scope module alu_tb $end
$var reg 8 ! a[7:0] $end
$var reg 8 " b[7:0] $end
$var reg 8 # dataout[7:0] $end
$var reg 8 $ operation[7:0] $end
$var reg 1 % clk $end
$var reg 1 & z $end
$var reg 1 ' ovf $end
$scope module uut $end
$var reg 8 ( operation[7:0] $end
$var reg 8 ) a[7:0] $end
$var reg 8 * b[7:0] $end
$var reg 1 + clk $end
$var reg 8 , dataout[7:0] $end
$var reg 1 - z $end
$var reg 1 . ovf $end
$upscope $end
$upscope $end
$enddefinitions $end
#0
b00000111 !
b00000000 "
b00000111 #
b00000000 $
U%
0&
0'
b00000000 (
b00000111 )
b00000000 *
U+
b00000111 ,
0-
0.
#1000000000
b00000110 !
b00000001 "
b00000110 )
b00000001 *
#2000000000
b00000101 !
b00000010 "
b00000101 )
b00000010 *
#3000000000
b00000100 !
b00000011 "
b00000100 )
b00000011 *
#4000000000
b00000011 !
b00000100 "
b00000011 )
b00000100 *
#5000000000
b00000010 !
b00000101 "
b00000010 )
b00000101 *
#6000000000
b00000001 !
b00000110 "
b00000001 )
b00000110 *
#7000000000
b00000000 !
b00000111 "
b00000000 )
b00000111 *
#8000000000
#9000000000
b00000000 "
b00000000 #
1&
b00000000 *
b00000000 ,
1-
#10000000000
b11111111 !
b00000001 "
0&
1'
b11111111 )
b00000001 *
0-
1.
#11000000000
b10101011 #
b10101011 $
1&
b10101011 (
b10101011 ,
1-
#12000000000
b00000000 "
b00000000 #
b00000001 $
0&
0'
b00000001 (
b00000000 *
b00000000 ,
0-
0.
#13000000000
b11110000 !
b00000001 "
b11110000 )
b00000001 *
#14000000000
b10101011 !
b11111111 "
b10101011 #
b10101011 )
b11111111 *
b10101011 ,
#15000000000
b11111111 !
b11111111 #
b11111111 )
b11111111 ,
