src/bank_register.vhd
library IEEE;
use IEEE.std_logic_1164.all;
use IEEE.numeric_std.all;

entity bank_register is
    

    port (
        A :     out std_logic_vector (15 downto 0);
        B :     out std_logic_vector (15 downto 0);
        D :     in std_logic_vector (15 downto 0);
        add_A:  in std_logic_vector (2 downto 0);
        add_B:  in std_logic_vector (2 downto 0);
        add_D:  in std_logic_vector (2 downto 0);
        WrD:    in STD_LOGIC;    
        Clk:    in STD_LOGIC
    );
    
end entity;

architecture arch of bank_register is

    subtype eWord is std_logic_vector (15 downto 0);
    type someWords is array (7 downto 0) of eWord;
    signal memory : someWords := (
        x"AAAA",
        x"BBBB",
        x"CCCC",
        x"DDDD",
        x"EEEE",
        x"FFFF",
        x"0000",
        x"1111"
    );
    
begin
    

   store: process(Clk)
   begin
     if rising_edge(Clk) then
            if WrD = '1' then
                memory(to_integer(unsigned(add_D))) <= D;
            end if;
     end if;
   end process;

    A <= memory(to_integer(unsigned(add_A)));
    B <= memory(to_integer(unsigned(add_B)));

end architecture;

src/bank_register_tb.vhd
library IEEE;
use IEEE.std_logic_1164.all;
use IEEE.numeric_std.all;
 

 
ENTITY bank_register_tb IS
END bank_register_tb;
 
ARCHITECTURE behavior OF bank_register_tb IS 
 
    -- Component Declaration for the Unit Under Test (UUT)
 
  

    COMPONENT bank_register is
        port (
            A :     out std_logic_vector (15 downto 0);
            B :     out std_logic_vector (15 downto 0);
            D :     in std_logic_vector (15 downto 0);
            add_A:  in std_logic_vector (2 downto 0);
            add_B:  in std_logic_vector (2 downto 0);
            add_D:  in std_logic_vector (2 downto 0);
            WrD:    in STD_LOGIC;    
            Clk:    in STD_LOGIC
        );
    END COMPONENT;
    

   --Inputs
   signal D : std_logic_vector(15 downto 0);
   signal add_A : std_logic_vector (2 downto 0);
   signal add_B : std_logic_vector (2 downto 0);
   signal add_D : std_logic_vector (2 downto 0);
   signal WrD:     STD_LOGIC;    
   signal Clk:    STD_LOGIC;

 	--Outputs
   signal A : std_logic_vector(15 downto 0);
   signal B : std_logic_vector(15 downto 0);
   
  
  



   -- No clocks detected in port list. Replace <clock> below with 
   -- appropriate port name 
 
   -- constant <clock>_period : time := 10 ns;
 
BEGIN
 
	-- Instantiate the Unit Under Test (UUT)
   uut: bank_register PORT MAP (
          A => A,
          B => B,
          D => D,
          WrD => WrD,
          Clk => Clk,
          add_A => add_A,
          add_B => add_B,
          add_D => add_D
        );

   -- Clock process definitions
   -- <clock>_process :process
   -- begin
	-- 	<clock> <= '0';
	-- 	wait for <clock>_period/2;
	-- 	<clock> <= '1';
	-- 	wait for <clock>_period/2;
   -- end process;
 

   -- Stimulus process
   stim_proc: process
   begin		
      -- hold reset state for 100 ns.
     -- wait for 1 ns;	

      -- wait for <clock>_period*10;

      -- insert stimulus here 
     
	    for i in 7 downto 0 loop
            WrD <= '0';
            Clk <= '0';
            add_A <= std_logic_vector(to_unsigned(i,add_A'length)); 
            add_B <= std_logic_vector(to_unsigned(10-i,add_B'length)); 
			wait for 1 us;
        end loop;
        add_D <= std_logic_vector(to_unsigned(0,add_D'length));
        D <= x"CAFE";
        WrD <= '1';
        Clk <= '1';
        wait for 1 us;
        Clk <= '0';
        add_A <= std_logic_vector(to_unsigned(0,add_A'length));
        wait for 1 us;

        add_B <= std_logic_vector(to_unsigned(1,add_B'length)); 
        add_D <= std_logic_vector(to_unsigned(1,add_D'length));
        D <= x"BEEF";
        WrD <= '1';
        Clk <= '1';
        wait for 1 us;
        Clk <= '0';
        add_B <= std_logic_vector(to_unsigned(1,add_B'length));
        wait for 1 us;
        for i in 7 downto 0 loop
            WrD <= '0';
            Clk <= '0';
            add_A <= std_logic_vector(to_unsigned(i,add_A'length)); 
            add_B <= std_logic_vector(to_unsigned(10-i,add_B'length)); 
			wait for 1 us;
        end loop;

      wait;
   end process;

END;

src/bank_register_tb.vcd
$date
  Wed Jan 26 17:57:48 2022
$end
$version
  GHDL v0
$end
$timescale
  1 fs
$end
$scope module standard $end
$upscope $end
$scope module textio $end
$upscope $end
$scope module std_logic_1164 $end
$upscope $end
$scope module numeric_std $end
$upscope $end
$scope module bank_register_tb $end
$var reg 16 ! d[15:0] $end
$var reg 3 " add_a[2:0] $end
$var reg 3 # add_b[2:0] $end
$var reg 3 $ add_d[2:0] $end
$var reg 1 % wrd $end
$var reg 1 & clk $end
$var reg 16 ' a[15:0] $end
$var reg 16 ( b[15:0] $end
$scope module uut $end
$var reg 16 ) a[15:0] $end
$var reg 16 * b[15:0] $end
$var reg 16 + d[15:0] $end
$var reg 3 , add_a[2:0] $end
$var reg 3 - add_b[2:0] $end
$var reg 3 . add_d[2:0] $end
$var reg 1 / wrd $end
$var reg 1 0 clk $end
$comment memory is not handled $end
$upscope $end
$upscope $end
$enddefinitions $end
#0
bUUUUUUUUUUUUUUUU !
b111 "
b011 #
bUUU $
0%
0&
b1010101010101010 '
b1110111011101110 (
b1010101010101010 )
b1110111011101110 *
bUUUUUUUUUUUUUUUU +
b111 ,
b011 -
bUUU .
0/
00
#1000000000
b110 "
b100 #
b1011101110111011 '
b1101110111011101 (
b1011101110111011 )
b1101110111011101 *
b110 ,
b100 -
#2000000000
b101 "
b101 #
b1100110011001100 '
b1100110011001100 (
b1100110011001100 )
b1100110011001100 *
b101 ,
b101 -
#3000000000
b100 "
b110 #
b1101110111011101 '
b1011101110111011 (
b1101110111011101 )
b1011101110111011 *
b100 ,
b110 -
#4000000000
b011 "
b111 #
b1110111011101110 '
b1010101010101010 (
b1110111011101110 )
b1010101010101010 *
b011 ,
b111 -
#5000000000
b010 "
b000 #
b1111111111111111 '
b0001000100010001 (
b1111111111111111 )
b0001000100010001 *
b010 ,
b000 -
#6000000000
b001 "
b001 #
b0000000000000000 '
b0000000000000000 (
b0000000000000000 )
b0000000000000000 *
b001 ,
b001 -
#7000000000
b000 "
b010 #
b0001000100010001 '
b1111111111111111 (
b0001000100010001 )
b1111111111111111 *
b000 ,
b010 -
#8000000000
b1100101011111110 !
b000 $
1%
1&
b1100101011111110 '
b1100101011111110 )
b1100101011111110 +
b000 .
1/
10
#9000000000
0&
00
#10000000000
b1011111011101111 !
b001 #
b001 $
1&
b1011111011101111 (
b1011111011101111 *
b1011111011101111 +
b001 -
b001 .
10
#11000000000
0&
00
#12000000000
b111 "
b011 #
0%
b1010101010101010 '
b1110111011101110 (
b1010101010101010 )
b1110111011101110 *
b111 ,
b011 -
0/
#13000000000
b110 "
b100 #
b1011101110111011 '
b1101110111011101 (
b1011101110111011 )
b1101110111011101 *
b110 ,
b100 -
#14000000000
b101 "
b101 #
b1100110011001100 '
b1100110011001100 (
b1100110011001100 )
b1100110011001100 *
b101 ,
b101 -
#15000000000
b100 "
b110 #
b1101110111011101 '
b1011101110111011 (
b1101110111011101 )
b1011101110111011 *
b100 ,
b110 -
#16000000000
b011 "
b111 #
b1110111011101110 '
b1010101010101010 (
b1110111011101110 )
b1010101010101010 *
b011 ,
b111 -
#17000000000
b010 "
b000 #
b1111111111111111 '
b1100101011111110 (
b1111111111111111 )
b1100101011111110 *
b010 ,
b000 -
#18000000000
b001 "
b001 #
b1011111011101111 '
b1011111011101111 (
b1011111011101111 )
b1011111011101111 *
b001 ,
b001 -
#19000000000
b000 "
b010 #
b1100101011111110 '
b1111111111111111 (
b1100101011111110 )
b1111111111111111 *
b000 ,
b010 -
